litestash/__init__.py
litestash/models.py
litestash/store.py
litestash/core/__init__.py
litestash/core/engine.py
litestash/core/schema.py
litestash/core/session.py
litestash/core/config/__init__.py
litestash/core/config/litestash_conf.py
litestash/core/config/model.py
litestash/core/config/root.py
litestash/core/config/schema_conf.py
litestash/core/config/tables/__init__.py
litestash/core/config/tables/tables_03.py
litestash/core/config/tables/tables_47.py
litestash/core/config/tables/tables_89hu.py
litestash/core/config/tables/tables_ab.py
litestash/core/config/tables/tables_cd.py
litestash/core/config/tables/tables_ef.py
litestash/core/config/tables/tables_gh.py
litestash/core/config/tables/tables_ij.py
litestash/core/config/tables/tables_kl.py
litestash/core/config/tables/tables_mn.py
litestash/core/config/tables/tables_op.py
litestash/core/config/tables/tables_qr.py
litestash/core/config/tables/tables_st.py
litestash/core/config/tables/tables_uv.py
litestash/core/config/tables/tables_wx.py
litestash/core/config/tables/tables_yz.py
litestash/core/util/__init__.py
litestash/core/util/litestash_util.py
litestash/core/util/model_util.py
litestash/core/util/prefix_util.py
litestash/core/util/schema_util.py
litestash/core/util/table_util.py
litestash-0.1.0b5.dist-info/LICENSE
litestash-0.1.0b5.dist-info/METADATA
litestash-0.1.0b5.dist-info/NOTICE
litestash-0.1.0b5.dist-info/WHEEL
litestash-0.1.0b5.dist-info/top_level.txt
litestash-0.1.0b5.dist-info/RECORD
