Metadata-Version: 2.1
Name: litestash
Version: 0.1.0b5
Summary: The LiteStash Python project offers a lightning-fast, lightweight key-value storage solution.  LiteStash provides a NoSQL API for seamless integration into your applications.  The LiteStash database handles the data with SQLite transparently.  Optimal use for caching, session management, and other high-performance use cases.
Author-email: Jonathan Cain <mail@mesotron.dev>
License: # Copyright 2024 Mesotron Machine Company LLC & the authors
Project-URL: Homepage, https://github.com/nortosem/LiteStash
Project-URL: Documentation, https://github.com/nortosem/LiteStash/blob/master/README.md
Classifier: Programming Language :: Python :: 3
Classifier: License :: OSI Approved :: Apache Software License
Classifier: Operating System :: OS Independent
Classifier: Development Status :: 4 - Beta
Classifier: Intended Audience :: Developers
Classifier: Topic :: Database
Classifier: Topic :: Software Development :: Libraries :: Python Modules
License-File: LICENSE
License-File: NOTICE
Requires-Dist: sqlalchemy >=2.0
Requires-Dist: annotated-types ==0.7.0
Requires-Dist: astroid ==3.2.3
Requires-Dist: coverage ==7.6.0
Requires-Dist: dill ==0.3.8
Requires-Dist: greenlet ==3.0.3
Requires-Dist: iniconfig ==2.0.0
Requires-Dist: isort ==5.13.2
Requires-Dist: mccabe ==0.7.0
Requires-Dist: orjson ==3.10.6
Requires-Dist: packaging ==24.1
Requires-Dist: platformdirs ==4.2.2
Requires-Dist: pluggy ==1.5.0
Requires-Dist: pydantic ==2.8.2
Requires-Dist: pydantic-core ==2.20.1
Requires-Dist: pylint ==3.2.5
Requires-Dist: pytest ==8.2.2
Requires-Dist: pytest-mock ==3.14.0
Requires-Dist: python-dotenv ==1.0.1
Requires-Dist: SQLAlchemy ==2.0.31
Requires-Dist: sqlmodel ==0.0.19
Requires-Dist: tomlkit ==0.13.0
Requires-Dist: typing-extensions ==4.12.2
